rtcam/__init__.py
rtcam-0.0.5.dist-info/METADATA
rtcam-0.0.5.dist-info/WHEEL
rtcam-0.0.5.dist-info/entry_points.txt
rtcam-0.0.5.dist-info/RECORD
