Metadata-Version: 2.4
Name: rtcam
Version: 0.0.5
Summary: Receiving frames from camera in subnet browsers via WebRTC
Author-email: uihp <plswrxtq@gmail.com>
Requires-Python: >=3.10
